pystubit/__init__.py
pystubit/button.py
pystubit-0.0.3.dist-info/METADATA
pystubit-0.0.3.dist-info/WHEEL
pystubit-0.0.3.dist-info/top_level.txt
pystubit-0.0.3.dist-info/RECORD
