Metadata-Version: 2.1
Name: pystubit
Version: 0.0.3
Summary: MicroPython library for StuduinoBit&ArtecRobo2.0
Home-page: https://github.com/artec-kk/pystuduino
Author: Artec Co., Ltd.
Author-email: support@artec-kk.co.jp
Maintainer: Artec Co., Ltd.
Maintainer-email: support@artec-kk.co.jp
License: UNKNOWN
Platform: UNKNOWN
